[
    {
        "name": "card_payment_wdddrong_exschange_rate",
        "intent_id": "ee67f3c3-488a-4c7d-ad7b-d5c66f471d52",
        "utterances": [
            "1. Can you provide information on how you determine exchange rates?",
            "2. What is the basis for your exchange rate calculations?",
            "3. How do you establish the exchange rates?",
            "4. Explain the method behind your exchange rate conversions.",
            "5. From what source do you obtain your exchange rate data?"
        ]
    },
    {
        "name": "card_payment_wrong_exchsange_rate",
        "intent_id": "5c5be5f6-8d6d-483b-b95b-b06d5b057135",
        "utterances": [
            "1. \"After making a purchase, I discovered an error in the currency exchange rate.\"",
            "2. \"The exchange rate employed is inaccurate.\"",
            "3. \"I request an adjustment to the exchange rate for a recent purchase made in a foreign currency.\"",
            "4. \"The exchange rate utilized in your application is highly unfavorable.\"",
            "5. \"I have concerns regarding the accuracy of the exchange rate applied to my recent transaction.\""
        ]
    },
    {
        "name": "extra_charge_on_statement",
        "intent_id": "bd899a56-53e3-4532-ab98-096d6cbc5fba",
        "utterances": [
            "1. Why is there an extra charge on my recent statement?",
            "2. I noticed an additional pound charged on my app. Can you clarify?",
            "3. I'm being charged an extra amount. Please provide an explanation.",
            "4. I was surprised to see a $1 charge on my recent transaction.",
            "5. My account has been charged an extra dollar, and it's showing as pending. Can you help me understand why?"
        ]
    },
    {
        "name": "pendin",
        "intent_id": "c48303b6-78bd-4320-b107-c883ea79b19c",
        "utterances": [
            "1. My withdrawal status is pending, when can I access the funds?",
            "2. Why is my cash withdrawal still pending?",
            "3. I'm unable to withdraw funds due to a pending transaction. Can you assist?",
            "4. Despite my withdrawal attempt being declined, the transaction remains pending. Please resolve this issue.",
            "5. Can you explain the reason behind pending withdrawals from my account?"
        ]
    },
    {
        "name": "fiat_currency_support",
        "intent_id": "f6800eb7-ae0e-498b-952e-a36cf20bae13",
        "utterances": [
            "1. Can you tell me when my ordered card will arrive? I'm expecting it soon.",
            "2. I need to know an estimated delivery time for my card order.",
            "3. Is there any way to expedite the delivery of my card?",
            "4. I'm concerned about the status of my card. When can I receive it?",
            "5. I've been waiting for my card for a while now. Can you provide an update?"
        ]
    },
    {
        "name": "casdhdhd",
        "intent_id": "5806862d-6fba-4c8e-879d-956afc5af877",
        "utterances": [
            "1. I've requested a card, but I haven't received it. When can I expect delivery?",
            "2. When will I get my physical card in the mail?",
            "3. My card is taking longer than expected. Can you tell me when it will arrive?",
            "4. I need my card as soon as possible. How quickly can you get it to me?",
            "5. How many days will it take for my card to arrive?"
        ]
    },
    {
        "name": "automatic_top_up",
        "intent_id": "7f8da5e9-3187-42d2-8012-59ebf4664562",
        "utterances": [
            "1. Enable automatic top-ups to avoid low balance scenarios.",
            "2. Can I configure automatic balance replenishment?",
            "3. Kindly assist me in setting up recurring top-up intervals.",
            "4. I would like to explore the possibility of an automated top-up system.",
            "5. Is there a feature that allows for automatic account balance maintenance?"
        ]
    },
    {
        "name": "card_not_working",
        "intent_id": "10c3377c-eda2-4828-a619-f9706486f49a",
        "utterances": [
            "1. My card isn't functioning correctly.",
            "2. I am having difficulty activating my card.",
            "3. The card is not operational.",
            "4. My card appears to be invalid or declined.",
            "5. I am encountering an issue with my card's usage."
        ]
    },
    {
        "name": "exchange_via_app",
        "intent_id": "ee95ae6f-c708-4eb1-b70a-7bf39e070569",
        "utterances": [
            "1. I'd like to convert my currency.",
            "2. I need to exchange currencies.",
            "3. Can I change the currency I'm exchanging?",
            "4. Is currency exchange possible via the app?",
            "5. How do I switch currencies in the app?"
        ]
    },
    {
        "name": "lost_or_stolen_card",
        "intent_id": "1739aa55-15c6-4493-935f-543f699ca18a",
        "utterances": [
            "1. My card is missing.",
            "2. I lost my card and need a new one.",
            "3. My card was stolen, please cancel it.",
            "4. Someone took my card, I need help.",
            "5. I believe my card was misappropriated."
        ]
    },
    {
        "name": "age_limit",
        "intent_id": "637c3adc-4f32-43fc-baa3-3103d4034ab4",
        "utterances": [
            "1. What is the minimum age to establish an account?",
            "2. How old must one be to be eligible for an account?",
            "3. Is there an age minimum to open an account?",
            "4. I'm interested in opening an account for a minor. What are the age restrictions?",
            "5. What is the age cutoff for account ownership?"
        ]
    },
    {
        "name": "pin_blocked",
        "intent_id": "7ecfcbde-3dc6-43e1-9eec-e9130378b6fa",
        "utterances": [
            "1. My PIN is blocked due to incorrect attempts.",
            "2. Can I reset my blocked PIN?",
            "3. How do I unblock my PIN after multiple failed attempts?",
            "4. I inadvertently exceeded my PIN attempts. How can I proceed?",
            "5. Requesting assistance to unblock my PIN."
        ]
    },
    {
        "name": "contactless_not_working",
        "intent_id": "10a9d14f-a932-43fe-bfe2-f7f2df0257da",
        "utterances": [
            "1. My contactless payment won't process.",
            "2. I'm having an issue with contactless payments.",
            "3. The contactless payment system isn't functioning.",
            "4. My card is not being accepted for contactless payments.",
            "5. I've attempted to use contactless payment, but it's unsuccessful."
        ]
    },
    {
        "name": "top_up_by_bank_transfer_charge",
        "intent_id": "cb8677f3-e21b-49d3-90dd-a4182f5ad467",
        "utterances": [
            "1. Are there additional charges for bank transfers?",
            "2. Do bank transfers incur a top-up fee?",
            "3. What is the surcharge for topping up using a bank transfer?",
            "4. Is there a cost associated with bank transfer top-ups?",
            "5. Are bank transfers subject to top-up charges?"
        ]
    },
    {
        "name": "pending_top_up",
        "intent_id": "5f8ef88b-66c8-41e2-8ffe-f7caa67483f3",
        "utterances": [
            "1. My top-up payment remains unprocessed.",
            "2. I have initiated a top-up, but it is still pending.",
            "3. Why is my recent top-up request still not reflected?",
            "4. I am concerned about the delay in processing my top-up.",
            "5. Can you investigate why my top-up is yet to be completed?"
        ]
    },
    {
        "name": "cancel_transfer",
        "intent_id": "abd708af-cade-42f0-8f8f-61fb8b599eaa",
        "utterances": [
            "1. I would like to cancel my latest transfer.",
            "2. Requesting cancellation of a transfer made in error.",
            "3. Stop the transfer I initiated earlier today.",
            "4. Can you please cancel a recent transfer I made?",
            "5. I need to cancel a transfer I just made due to an incorrect account number."
        ]
    },
    {
        "name": "top_up_limits",
        "intent_id": "e774870c-8bde-4036-aefd-c356af2dc02a",
        "utterances": [
            "1. I'm curious, is there a cap on how much I can top up?",
            "2. Can you tell me the max number of top-ups I'm allowed?",
            "3. What's the limit on top-up amounts?",
            "4. Are there restrictions on the frequency of top-ups?",
            "5. How often am I allowed to make top-ups?"
        ]
    },
    {
        "name": "wrong_amount_of_cash_received",
        "intent_id": "79740d91-cb4b-411c-993d-c0664ad5f504",
        "utterances": [
            "1. The ATM gave me less money than I requested, but the transaction history shows the correct amount.",
            "2. I only received $50 from the ATM, but the app is showing a withdrawal of $100.",
            "3. The ATM dispensed incorrect cash. I asked for $200, but I only got $180.",
            "4. I withdrew money from the ATM, but the amount I received doesn't match what's on the receipt.",
            "5. Hey, the ATM gave me the wrong amount of cash when I made a withdrawal. The app is showing the right amount, though."
        ]
    },
    {
        "name": "card_payment_fee_charged",
        "intent_id": "78fc3d36-8c89-4199-bf9a-9d62eb78db58",
        "utterances": [
            "1. Is a surcharge applied to my card transactions?",
            "2. I was unexpectedly charged a fee for using my card.",
            "3. I've noticed a fee associated with my card payments.",
            "4. I've been charged a fee after making a card purchase.",
            "5. Can you clarify why I've been charged a fee for using my card?"
        ]
    },
    {
        "name": "transfer_not_received_by_recipient",
        "intent_id": "ce4eadff-fc0b-4844-8fc6-7d1d5311e03a",
        "utterances": [
            "1. The transfer I sent has not been received by the recipient.",
            "2. The transfer made to [recipient's name] has gone missing.",
            "3. I've experienced a discrepancy in a recent transfer, as the recipient has not received the funds.",
            "4. Despite sending the transfer promptly, it appears to have stalled during processing.",
            "5. The status of my transfer is concerning, as the intended recipient has yet to acknowledge receipt."
        ]
    },
    {
        "name": "supported_cards_and_currencies",
        "intent_id": "0ac9bb03-395c-4021-b4aa-f1b1ff6b3ee5",
        "utterances": [
            "1. Which payment options are supported?",
            "2. What currencies and cards can I use?",
            "3. Can I add funds using my American Express card?",
            "4. How do I deposit using my preferred card?",
            "5. Are there any limitations on the payment methods accepted?"
        ]
    },
    {
        "name": "getting_virtual_card",
        "intent_id": "bada62b0-323b-49ae-92ff-c0a8768d772e",
        "utterances": [
            "1. I'm still waiting for my virtual card to arrive.",
            "2. When can I expect my virtual card?",
            "3. I haven't received a virtual card yet.",
            "4. Can you help me track the status of my virtual card?",
            "5. I'd like to know when I can access my virtual card."
        ]
    },
    {
        "name": "card_acceptance",
        "intent_id": "38fd54db-020e-469c-ba54-b8a5f721065b",
        "utterances": [
            "1. Where is my card accepted?",
            "2. What businesses accept my card?",
            "3. Show me a list of places that take this card.",
            "4. I need to know if I can use my card here.",
            "5. Which locations accept my payment card?"
        ]
    },
    {
        "name": "top_up_reverted",
        "intent_id": "49a13503-a1e9-4571-a7f2-089d83aa173e",
        "utterances": [
            "1. My top-up transaction was reversed.",
            "2. I topped up but the money was removed.",
            "3. The top-up I made is no longer showing in my account.",
            "4. I'm missing a recent top-up that disappeared from my account.",
            "5. I recently made a top-up, but it has been canceled."
        ]
    },
    {
        "name": "balance_not_updated_after_cheque_or_cash_deposit",
        "intent_id": "e7031def-5d14-4e01-afd4-3f1ec7667955",
        "utterances": [
            "1. My balance should be higher after the cash deposit, but it hasn't changed.",
            "2. I made a cheque deposit but my account balance doesn't reflect it.",
            "3. I can't find the cash I deposited in my account earlier.",
            "4. Why hasn't my balance been updated after the deposit I made?",
            "5. I'm concerned because my deposited cheque has not yet shown up in my account."
        ]
    },
    {
        "name": "card_payment_not_recognised",
        "intent_id": "4453865b-dc8f-4725-a4f9-fb065b1a2b8a",
        "utterances": [
            "1. I've noticed a payment on my card that I don't recognize.",
            "2. There seems to be a mistake in my bank statement. I don't recognize a transaction.",
            "3. A payment has been made from my account that I did not authorize.",
            "4. I'm concerned about a recent charge on my card that I didn't make.",
            "5. I believe there's an unauthorized transaction on my account."
        ]
    },
    {
        "name": "edit_personal_details",
        "intent_id": "a1000ca1-551b-47e6-ab1e-ac62f1049514",
        "utterances": [
            "1. I want to modify my personal information.",
            "2. I need to update certain details on my profile.",
            "3. Can I make changes to my existing account data?",
            "4. I request access to edit my personal information.",
            "5. I wish to update my profile with new contact specifics."
        ]
    },
    {
        "name": "why_verify_identity",
        "intent_id": "d7d72d6d-69e6-46fe-b36b-2de9f0c24de3",
        "utterances": [
            "1. What's the reason for needing to verify my identity?",
            "2. Why do you ask for my identification documents?",
            "3. Can you explain why identity verification is required?",
            "4. I don't understand why my identity needs to be verified.",
            "5. Why do I need to provide so much personal information to verify my identity?"
        ]
    },
    {
        "name": "unable_to_verify_identity",
        "intent_id": "9ce14e10-0a9b-4e5f-8d75-3f77e14077e3",
        "utterances": [
            "1. Identity verification is encountering difficulties.",
            "2. I am unable to complete the identity verification process.",
            "3. The information provided for identity verification is not being accepted.",
            "4. What must I do to successfully verify my identity?",
            "5. I lack the necessary information to verify my identity."
        ]
    },
    {
        "name": "get_physical_card",
        "intent_id": "aee9945b-70ff-4a1c-ab1e-ed6046160a80",
        "utterances": [
            "1. When can I expect to receive my physical card and PIN?",
            "2. I've been waiting for my card's PIN. Can you tell me an estimated arrival time?",
            "3. How do I retrieve my physical card PIN?",
            "4. I'm expecting a physical card with a PIN. Can you confirm the shipment status?",
            "5. When will my physical card and PIN be delivered?"
        ]
    },
    {
        "name": "visa_or_mastercard",
        "intent_id": "faa2da25-1ccb-4327-b98c-e2d3bc43b01b",
        "utterances": [
            "1. Do I have the option to use a Visa or Mastercard?",
            "2. Can I obtain a Visa or Mastercard through your services?",
            "3. Can I acquire a Visa card?",
            "4. I would like to inquire about both Visa and Mastercard options.",
            "5. Is it feasible to receive a Mastercard and Visa from your company?"
        ]
    },
    {
        "name": "topping_up_by_card",
        "intent_id": "d98482dc-d4c1-41cb-8258-c15c50b4fc4c",
        "utterances": [
            "1. Can I add funds to my account using a card?",
            "2. How can I top up my balance with a credit/debit card?",
            "3. Can you guide me through topping up by card?",
            "4. I want to add to my account using my card. Can you help?",
            "5. Is it feasible to use a card to fund my account?"
        ]
    },
    {
        "name": "disposable_card_limits",
        "intent_id": "0cfc97b6-f6fd-48dc-a8f1-52a797fedb26",
        "utterances": [
            "1. How many disposable cards can I use daily?",
            "2. What's the daily limit for disposable virtual cards?",
            "3. Show me the limitations on disposable card transactions.",
            "4. Is there a limit to the amount I can spend using disposable cards?",
            "5. Tell me about the restrictions for using disposable cards."
        ]
    },
    {
        "name": "compromised_card",
        "intent_id": "21980825-b8d0-4d36-a172-14da4d14e85c",
        "utterances": [
            "1. I'm concerned that my card may have been compromised.",
            "2. I suspect unauthorized purchases have been made with my card.",
            "3. Someone seems to be using my card without my authorization.",
            "4. I've noticed suspicious transactions that I didn't make.",
            "5. I fear my card information may have been compromised and used fraudulently."
        ]
    },
    {
        "name": "atm_support",
        "intent_id": "b55f1ae6-0a34-4f73-833b-24cad84f688c",
        "utterances": [
            "1. Can I withdraw from any ATM with this card?",
            "2. Which ATMs are compatible with my card?",
            "3. Are my card services supported by nearby ATMs?",
            "4. Where can I find cash withdrawal points for my card?",
            "5. Help me locate ATMs that accept this card."
        ]
    },
    {
        "name": "direct_debit_payment_not_recognised",
        "intent_id": "b80f272a-8308-47d7-bd38-92614babc61f",
        "utterances": [
            "1. Um, this direct debit doesn't look right.",
            "2. I'm wondering about this direct debit that's come out.",
            "3. Can you help me identify a direct debit I don't recognize?",
            "4. There's a charge in my bank account that I can't explain.",
            "5. I'm getting charged for something I don't remember signing up for."
        ]
    },
    {
        "name": "passcode_forgotten",
        "intent_id": "f14e398f-4508-45e4-b73a-25336722d38f",
        "utterances": [
            "1. I've forgotten my passcode.",
            "2. Can you help me, I've lost my passcode?",
            "3. I'm having trouble entering my passcode.",
            "4. My passcode isn't working, I think I may have forgotten it.",
            "5. I don't remember my passcode, what can I do?"
        ]
    },
    {
        "name": "declined_cash_withdrawal",
        "intent_id": "3386aaf1-4933-4a0d-bf70-e0f730a9c080",
        "utterances": [
            "1. ATM declined my cash withdrawal.",
            "2. I got declined using an ATM.",
            "3. My cash withdrawal request wasn't successful.",
            "4. The ATM machine rejected my cash withdrawal.",
            "5. I couldn't withdraw cash at the ATM."
        ]
    },
    {
        "name": "pending_card_payment",
        "intent_id": "280a2a02-307a-4784-b7fe-ba19baa0666d",
        "utterances": [
            "1. I made a card payment that's stuck in progress.",
            "2. What's up with my payment? It's showing as pending.",
            "3. My card payment isn't going through yet.",
            "4. I'm trying to understand why my payment is still pending.",
            "5. When will the pending payment I made yesterday be processed?"
        ]
    },
    {
        "name": "lost_or_stolen_phone",
        "intent_id": "518a7a48-8e03-459c-a583-06d365a0a4a3",
        "utterances": [
            "1. **Formal:** I regret to inform you that my mobile device has been misappropriated.",
            "2. **Informal:** My phone has been snatched! Help!",
            "3. **Urgent:** Urgent assistance required! My phone has vanished yesterday.",
            "4. **Specific:** I have misplaced my phone, rendering the app inaccessible.",
            "5. **Cautious:** I suspect my phone is no longer in my possession. Is there a mechanism to safeguard my account?"
        ]
    },
    {
        "name": "request_refund",
        "intent_id": "4c1e31f7-c1ab-413e-a6dc-227c0e8f2a6c",
        "utterances": [
            "1. Can I get a refund on my last order?",
            "2. Hey, I need to cancel an order and get my money back.",
            "3. I want to return something I bought and get a refund.",
            "4. How can I request a refund for an item I haven't received?",
            "5. I'd like to get a refund for a purchase I made by mistake."
        ]
    },
    {
        "name": "declined_transfer",
        "intent_id": "4ae42ceb-409e-47b3-8e70-02c8e6a4494f",
        "utterances": [
            "1. My transfer didn't go through, can you explain why?",
            "2. I tried to make a transfer but it was declined.",
            "3. Why was my recent transfer denied?",
            "4. I'm confused as to why my transfer was unsuccessful.",
            "5. Can you tell me the reason behind my failed transfer?"
        ]
    },
    {
        "name": "Refund_not_showing_up",
        "intent_id": "059e525b-f918-4943-9b45-b2d4e982b302",
        "utterances": [
            "1. My refund appears to be missing or delayed.",
            "2. I haven't received my refund yet, and I'm starting to worry.",
            "3. Where's my refund? It's not in my bank account.",
            "4. I've been waiting for my refund for a while now, but it hasn't arrived.",
            "5. I'm concerned because I don't see my refund in my bank account statement."
        ]
    },
    {
        "name": "declined_card_payment",
        "intent_id": "7630ceae-718f-40e4-b544-d1b354895038",
        "utterances": [
            "1. My card isn't going through, what's wrong?",
            "2. I'm unable to make a card payment, can you help?",
            "3. My card was rejected when I tried to pay.",
            "4. Why was my card declined for this purchase?",
            "5. I'm having trouble completing my transaction, my card isn't being accepted."
        ]
    },
    {
        "name": "pending_transfer",
        "intent_id": "9e790fc1-111f-444b-8861-765d7b3a5887",
        "utterances": [
            "1. My funds are still pending transfer, when can I expect them?",
            "2. Why is my transfer showing as pending for so long?",
            "3. I sent a transfer yesterday and it's still not completed. Is there a problem?",
            "4. The recipient hasn't received the funds and the transfer is stuck on pending.",
            "5. How can I get an update on the status of my pending transfer?"
        ]
    },
    {
        "name": "terminate_account",
        "intent_id": "1564e63f-2634-4f2c-ac94-59750ba2f25e",
        "utterances": [
            "1. I'd like to terminate my account effective immediately.",
            "2. I'm requesting the permanent closure of my account.",
            "3. Please delete my account. I'm dissatisfied with the service I've received.",
            "4. I want to end my account. I'm not interested in continuing to use it.",
            "5. I hereby request the cancellation of my account."
        ]
    },
    {
        "name": "card_swallowed",
        "intent_id": "5bf54aeb-d43c-4de0-9766-dcbf0138caa1",
        "utterances": [
            "1. My card got stuck in the ATM.",
            "2. I can't retrieve my card from the ATM.",
            "3. The ATM swallowed my card, and I'm unable to get it out.",
            "4. The bank machine took my card and won't return it.",
            "5. I've inserted my card into the ATM, but it's not being released."
        ]
    },
    {
        "name": "transaction_charged_twice",
        "intent_id": "dbcf847a-5f7a-4ab0-ab6b-5f5a2dcb44f2",
        "utterances": [
            "1. **Formal:** I have noticed an irregularity in my account with charges appearing in duplicate.",
            "2. **Informal:** My card was denied, but I'm seeing multiple charges on my statement?",
            "3. **Phrased Differently:** There have been recurring instances of the same transaction on my account.",
            "4. **Query:** Why have I been billed for the same transaction more than once?",
            "5. **Statement:** My account reflects multiple charges for a single transaction."
        ]
    },
    {
        "name": "verify_source_of_funds",
        "intent_id": "f7254dbe-e9f0-43cb-8c34-8cf43e627d5f",
        "utterances": [
            "1. Determine the origin of my funds.",
            "2. Establish the provenance of my financial resources.",
            "3. Ascertain the source or source(s) underlying my available funds.",
            "4. Verify the point of origin for the funds in my possession.",
            "5. Confirm the genesis of my financial holdings."
        ]
    },
    {
        "name": "transfer_timing",
        "intent_id": "10fcedb5-0dca-4b21-a8f3-25b5dbb8b892",
        "utterances": [
            "1. When will my recently initiated transfer be available?",
            "2. I'm inquiring about the timeline for my transfer from the United States.",
            "3. How long should I expect to wait for my transfer from the US to arrive?",
            "4. Could you provide an estimate of the processing time for an international transfer from Europe?",
            "5. I initiated a transfer yesterday, could you please confirm the estimated arrival time?"
        ]
    },
    {
        "name": "reverted_card_payment?",
        "intent_id": "385509fa-990b-4342-a510-bbf42fd6d960",
        "utterances": [
            "1. I see a payment that was reversed, but I don't know why.",
            "2. My payment was taken from my account, but I just received the funds again.",
            "3. I used my card to pay for something, but now I see the money back in my account.",
            "4. I'm confused. I made a card payment, but now the money is back.",
            "5. I'm concerned because my card payment was processed, but now the funds are back in my account."
        ]
    },
    {
        "name": "change_pin",
        "intent_id": "58dace7a-c513-4e27-81f9-ab47a9ad4d79",
        "utterances": [
            "1. How do I change the PIN for my bank card?",
            "2. Can I change my PIN number remotely?",
            "3. I need to update my card's PIN. Can you guide me through the process?",
            "4. I forgot my PIN and want to set a new one. Is there an online option?",
            "5. How can I change my banking PIN without visiting a branch?"
        ]
    },
    {
        "name": "beneficiary_not_allowed",
        "intent_id": "6dba7b83-3ac5-4afb-94dc-a65f6fd16e13",
        "utterances": [
            "1. My transfer attempts have consistently failed. Is there a reason for this?",
            "2. Can you provide an explanation for the rejection of this beneficiary?",
            "3. I'm having difficulty adding a particular beneficiary. What restrictions apply?",
            "4. Why am I unable to process a payment to this recipient?",
            "5. Could you assist me in understanding the factors contributing to the ineligibility of my beneficiary?"
        ]
    },
    {
        "name": "transfer_fee_charged",
        "intent_id": "0459d2b3-9a39-490d-b2e0-645007101c2e",
        "utterances": [
            "1. Transfer incurred an unexpected fee.",
            "2. I've been charged for transferring funds.",
            "3. Why am I being charged a transfer fee?",
            "4. I'm disputing the fee charged for my transfer.",
            "5. There was an unwarranted fee attached to my transfer."
        ]
    },
    {
        "name": "receiving_money",
        "intent_id": "23e8696e-ca0e-478a-978c-9e2f428b9b5a",
        "utterances": [
            "1. Can I receive payments in a different currency?",
            "2. Is there a limit on how much money I can receive?",
            "3. How do I set up a way for my friend to send me funds?",
            "4. Is it possible to receive my paycheck directly into this account?",
            "5. What's the preferred method for receiving money transfers?"
        ]
    },
    {
        "name": "failed_transfer",
        "intent_id": "65451cf4-f998-4c8b-b66a-ed7dc94de94e",
        "utterances": [
            "1. \"My recent transfer attempts have been unsuccessful.\"",
            "2. \"Despite repeated attempts, I am unable to complete the transfer.\"",
            "3. \"I've encountered a persistent issue impeding the completion of my transfer.\"",
            "4. \"Kindly investigate the reason behind my unsuccessful transfer.\"",
            "5. \"Transfer error: Please assist in resolving.\""
        ]
    },
    {
        "name": "transfer_into_account",
        "intent_id": "29a0f766-8b96-4535-bdab-9ccaf0146b51",
        "utterances": [
            "1. Can I transfer funds to my account?",
            "2. How can I move money into my account using your platform?",
            "3. What options are available for transferring funds to my account?",
            "4. I need guidance on transferring money to my account, can you assist?",
            "5. I'd like to top up my account via transfer, could you provide instructions?"
        ]
    },
    {
        "name": "verify_top_up",
        "intent_id": "f6b5b4e0-ee96-433a-bb6d-71231b9d933f",
        "utterances": [
            "1. I need help verifying a recent phone top-up.",
            "2. Show me how to confirm the top-up I just made.",
            "3. I can't locate the verification number for my latest top-up.",
            "4. Can you guide me through verifying the top-up I recently made?",
            "5. How do I check if my most recent top-up has been processed?"
        ]
    },
    {
        "name": "getting_spare_card",
        "intent_id": "47b35f39-23fc-4149-a2d6-6d3e8bc3b047",
        "utterances": [
            "1. I need an additional card.",
            "2. Can I obtain a supplementary card?",
            "3. I'd like to request an extra card.",
            "4. Is it possible to issue me with a spare card?",
            "5. I'm interested in getting another card."
        ]
    },
    {
        "name": "top_up_by_cash_or_cheque",
        "intent_id": "30c03a59-b9f9-406c-ae91-0186d214137f",
        "utterances": [
            "1. I'd like to deposit cash today.",
            "2. Can I top up my account with a cheque?",
            "3. I have some cash I want to put into my account.",
            "4. What's the procedure for topping up with cash?",
            "5. I'm looking to deposit a cheque, how should I go about it?"
        ]
    },
    {
        "name": "order_physical_card",
        "intent_id": "5cb18936-a3b1-4e2e-b21b-1da9c985edeb",
        "utterances": [
            "1. Formal: I respectfully request the issuance of a physical debit card.",
            "2. Neutral: I would like to obtain a physical card.",
            "3. Casual: I need to get my hands on a physical card.",
            "4. Urgent: I'm requesting a physical card, please. I'm waiting for it.",
            "5. Polite: Excuse me, but I'm hoping to receive a physical card."
        ]
    },
    {
        "name": "virtual_card_not_working",
        "intent_id": "06abdc9c-ab40-4136-bb43-a0a5e11ff04f",
        "utterances": [
            "1. I'm unable to use my virtual card for payments.",
            "2. The virtual card I created is not processing transactions.",
            "3. My virtual card appears to be malfunctioning.",
            "4. I'm experiencing issues with my virtual card functionality.",
            "5. The virtual card I generated is not allowing me to make purchases."
        ]
    },
    {
        "name": "wrong_exchange_rate_for_cash_withdrawal",
        "intent_id": "641281fc-4bfa-4964-a715-bece119aadee",
        "utterances": [
            "1. The currency exchange rate for my recent cash withdrawal is incorrect.",
            "2. I suspect an error in the exchange rate applied to my cash withdrawal.",
            "3. I believe an incorrect exchange rate was used when I withdrew the cash.",
            "4. I withdrew cash recently and it appears the exchange rate was grossly inaccurate.",
            "5. I need information on the exchange rates for cash withdrawals."
        ]
    },
    {
        "name": "get_disposable_virtual_card",
        "intent_id": "423d5858-7627-462e-8a34-8d0cd6f265bc",
        "utterances": [
            "1. I'd like to get a virtual card I can discard after using it.",
            "2. Can you assist me with creating a temporary virtual card?",
            "3. Is it possible to obtain a disposable virtual credit card?",
            "4. I need a virtual card that I can use once and then discard. How do I get one?",
            "5. I'm looking for a single-use virtual card for an online purchase. Can you guide me?"
        ]
    },
    {
        "name": "top_up_failed",
        "intent_id": "8311e881-11b7-41c7-9c3f-b518f7926b61",
        "utterances": [
            "1. The top-up failed for some reason. Can you help?",
            "2. Why wasn't my top-up successful? I followed the instructions.",
            "3. My credit card top-up didn't work. What's wrong?",
            "4. I'm not sure why, but I can't seem to top up my account right now.",
            "5. I tried to add credit using my card, but it says the transaction failed."
        ]
    },
    {
        "name": "balance_not_updated_after_bank_transfer",
        "intent_id": "771d2ec6-3763-4e03-af5e-30d711fa8853",
        "utterances": [
            "1. I transferred funds, but they're not reflected in my account balance.",
            "2. Can you confirm the expected timeframe for a transfer from a UK bank account?",
            "3. I've completed a transfer, but the funds are not yet visible in my account.",
            "4. I need assistance with a recent transfer as the balance hasn't updated.",
            "5. Despite transferring money into my account, the funds have not been credited."
        ]
    },
    {
        "name": "cash_withdrawal_not_recognised",
        "intent_id": "41bee67c-dd7c-47bd-9e73-f72371d992e5",
        "utterances": [
            "1. There's a cash withdrawal on my account that I didn't make.",
            "2. I'm seeing a withdrawal I don't recognize on my account history.",
            "3. I've just noticed a cash withdrawal that I'm not familiar with.",
            "4. I have a withdrawal on my statement that I didn't authorize.",
            "5. Can you help me? I've had a cash withdrawal that I didn't do."
        ]
    },
    {
        "name": "exchange_charge",
        "intent_id": "7962dfa2-0c9e-4755-b670-a0a9153f1393",
        "utterances": [
            "1. What's the exchange charge for converting my currency?",
            "2. Can you inform me about the fees associated with exchanging foreign money?",
            "3. I'm interested in exchanging currency, how much will it cost?",
            "4. Do you charge a fee for currency exchange transactions?",
            "5. I'd like to know the specific exchange rate and any additional charges for currency conversion."
        ]
    },
    {
        "name": "top_up_by_card_charge",
        "intent_id": "c4e95951-7207-469e-b7dd-8a84c2f407e0",
        "utterances": [
            "1. What fees apply when I top up with a foreign card?",
            "2. Are there any charges for adding funds via credit card?",
            "3. I want to use my overseas card for a top-up. Are there any fees?",
            "4. Can you tell me about the fees for using a non-native bank card to top up?",
            "5. Are there any hidden fees if I top up my account with an international card?"
        ]
    },
    {
        "name": "activate_my_card",
        "intent_id": "a494bca3-bad8-4ad8-a891-5710fcbe124f",
        "utterances": [
            "1. Hey, can you help me activate my new card?",
            "2. I'm having trouble activating my card.",
            "3. I need to get my card working.",
            "4. How do I activate my card so I can start using it?",
            "5. I want to activate my card, please."
        ]
    },
    {
        "name": "cash_withdrawal_charge",
        "intent_id": "0525eac5-e1e2-40b7-a08d-a991c908beda",
        "utterances": [
            "1. I was surprised to see a charge for taking out cash from the ATM.",
            "2. I'd like to know why I'm being charged for withdrawing my own money.",
            "3. Can you clarify why there's a fee associated with cash withdrawals?",
            "4. I recently made a cash withdrawal and noticed a charge on my account.",
            "5. How much will I be charged if I make a cash withdrawal from my account?"
        ]
    },
    {
        "name": "card_about_to_expire",
        "intent_id": "2884ff37-1429-4606-9264-78709a84d39d",
        "utterances": [
            "1. My card is set to expire soon, what are my options?",
            "2. When my card expires, how much will it cost to replace it?",
            "3. What happens after my card expires? Do I need to do anything?",
            "4. How long will it take to get a new card if my current one expires soon?",
            "5. I'm concerned about my card expiring. What should I do?"
        ]
    },
    {
        "name": "apple_pay_or_google_pay",
        "intent_id": "b6d427f6-96de-4d9a-90d6-2c5e34db9ef1",
        "utterances": [
            "1. I'd like to pay using my mobile wallet.",
            "2. Can I use Apple Pay or Google Pay to top up?",
            "3. I want to top up with one of the mobile payment services.",
            "4. I'm having trouble linking my Google Pay account.",
            "5. Is there an option to add funds using Apple Pay?"
        ]
    },
    {
        "name": "verify_my_identity",
        "intent_id": "e47cef8d-24da-4472-b521-c3f71149d60e",
        "utterances": [
            "1. Please guide me through the process of establishing my identity.",
            "2. I need assistance with verifying my identity.",
            "3. How can I confirm my identity?",
            "4. Provide me with instructions for completing the identity verification.",
            "5. Outline the requirements for verifying my identity."
        ]
    },
    {
        "name": "country_support",
        "intent_id": "b7b93969-df72-46a8-80bc-5be65ba8561c",
        "utterances": [
            "1. **Formal:** What geographical territories does your organization provide support for?",
            "2. **Semi-formal:** Are there any geographic limitations to your services?",
            "3. **Casual:** Which countries can I use your services in?",
            "4. **Conversational:** Do your cards work internationally?",
            "5. **Scenario-based:** I'm relocating to a different country. Can I still use your services there?"
        ]
    }
]